{
    "midi_file_path": "archive-new\\883\\Rotta_x_casa_di_Dio.mid",
    "artist_band_name": "883",
    "song_title": "Rotta x casa di Dio",
    "lyrics": {
        "Verse": [],
        "Chorus": [],
        "Pre-Chorus": [],
        "Bridge": []
    },
    "spotify_metadata": {
        "energy": 0.818,
        "acousticness": 0.089,
        "danceability": 0.642,
        "instrumentalness": 0,
        "liveness": 0.0973,
        "speechiness": 0.0364,
        "loudness": -7.454,
        "tempo": 121.263,
        "time_signature": 4,
        "valence": 0.734,
        "genre": [
            "italian adult pop"
        ],
        "popularity": 51
    }
}