{
    "midi_file_path": "archive-new\\a-ha\\Take_On_Me.2.mid",
    "artist_band_name": "a-ha",
    "song_title": "Take On Me.2",
    "lyrics": {
        "Verse": [
            "We're talkin' away",
            "I don't know what I'm to say",
            "I'll say it anyway",
            "Today's another day to find you",
            "Shying away",
            "I'll be comin' for your love, okay?",
            "",
            "So, needless to say",
            "I'm odds and ends",
            "But I'll be stumbling away",
            "Slowly learnin' that life is okay",
            "Say after me",
            "\"It's no better to be safe than sorry\"",
            "",
            "Oh, things that you say, yeah",
            "Is it life or just to play my worries away?",
            "You're all the things I've got to remember",
            "You're shying away",
            "I'll be comin' for you anyway",
            ""
        ],
        "Chorus": [
            "Take on me (Take on me)",
            "Take me on (Take on me)",
            "I'll be gone",
            "In a day or two",
            "",
            "Take on me (Take on me)",
            "Take me on (Take on me)",
            "I'll be gone",
            "In a day or two",
            "You might also like[Instrumental Break]",
            "",
            "Take on me (Take on me)",
            "Take me on (Take on me)",
            "I'll be gone",
            "In a day",
            "",
            "[Outro]",
            "(Take on me) (Take on me)",
            "(Take me on) (Take on me)",
            "I'll be gone (Take on me) (Take on me)",
            "In a day (Take me on) (Take on me)",
            "(Take on me) (Take on me)",
            "(Take me on) (Take on me)",
            "(Take on...)97Embed"
        ],
        "Pre-Chorus": [],
        "Bridge": []
    },
    "spotify_metadata": {
        "energy": 0.188,
        "acousticness": 0.92,
        "danceability": 0.437,
        "instrumentalness": 1.26e-05,
        "liveness": 0.0988,
        "speechiness": 0.0307,
        "loudness": -10.868,
        "tempo": 103.883,
        "time_signature": 5,
        "valence": 0.223,
        "genre": [
            "new romantic",
            "new wave",
            "new wave pop",
            "permanent wave",
            "synthpop"
        ],
        "popularity": 62
    }
}