{
    "midi_file_path": "archive-new\\Alice_Cooper\\You_and_Me.mid",
    "artist_band_name": "Alice Cooper",
    "song_title": "You and Me",
    "lyrics": {
        "Verse": [
            "When I get home from work",
            "I wanna wrap myself around you",
            "I wanna take you and squeeze you",
            "'Til the passion starts to rise",
            "",
            "Sometimes when you're asleep",
            "And I'm just starin' at the ceiling",
            "I wanna reach out and touch you",
            "But you just go on dreamin'",
            "",
            "When I get home from work",
            "I wanna wrap myself around you",
            "I'd like to hold you, squeeze you",
            "'Til the passion starts to rise",
            ""
        ],
        "Chorus": [
            "I wanna take you to heaven",
            "That would make my day complete",
            "",
            "But you and me ain't no movie stars",
            "What we are is what we are",
            "We share a bed, some lovin' and TV, yeah",
            "And that's enough for a workin' man",
            "What I am is what I am",
            "And I tell you, babe, well that's enough for me",
            "",
            "If I could take you to heaven",
            "That would make my day complete",
            "But you and me ain't no movie stars",
            "What we are is what we are",
            "We share a bed, some lovin' and TV, yeah",
            "'Cause that's enough for a workin' man",
            "What I am is what I am",
            "And I tell you, sweetheart, that's just enough for me",
            "",
            "[Instrumental Break]",
            "",
            "You and me ain't no superstars",
            "What we are is what we are",
            "We share a bed, some popcorn and TV, yeah",
            "And that's enough for a workin' man",
            "What I am is what I am",
            "And I tell you, babe, you're just enough for me",
            "",
            "I wanna take you to heaven",
            "That would make my day complete",
            "You and me ain't no movie stars",
            "What we are is what we are",
            "We share a bed, some lovin' and TV, yeah",
            "And that's enough for a workin' man",
            "What I am, well that's what I am",
            "I tell you, baby, that's just enough for meEmbed"
        ],
        "Pre-Chorus": [],
        "Bridge": []
    },
    "spotify_metadata": {
        "energy": 0.317,
        "acousticness": 0.369,
        "danceability": 0.613,
        "instrumentalness": 0.000288,
        "liveness": 0.0775,
        "speechiness": 0.0293,
        "loudness": -16.102,
        "tempo": 113.124,
        "time_signature": 4,
        "valence": 0.473,
        "genre": [
            "album rock",
            "classic rock",
            "detroit rock",
            "glam metal",
            "glam rock",
            "hard rock",
            "metal",
            "protopunk",
            "rock"
        ],
        "popularity": 47
    }
}