{
    "midi_file_path": "archive-new\\Alice_Cooper\\How_You_Gonna_See_Me_Now.mid",
    "artist_band_name": "Alice Cooper",
    "song_title": "How You Gonna See Me Now",
    "lyrics": {
        "Verse": [
            "Dear darlin', surprised to hear from me?",
            "Bet you're sittin' drinkin' coffee, yawnin' sleepily",
            "Just to let you know I'm gonna be home soon",
            "I'm kinda awkward and afraid time has changed your point of view",
            "",
            "Listen darlin', now I'm heading for the west",
            "Straightened out my head but my old heart is still a mess",
            "Yes, I'm worried, honey, guess that's natural though",
            "It's like I'm waiting for a welcome sign like a hobo in the snow",
            ""
        ],
        "Chorus": [
            "How you gonna see me now?",
            "Please don't see me ugly, babe",
            "'Cause I know I let you down",
            "In, oh, so many ways",
            "How you gonna see me now?",
            "Since we've been on our own",
            "Are you gonna love the man",
            "When the man gets home?",
            "",
            "How you gonna see me now?",
            "Please don't see me ugly, babe",
            "'Cause I know I let you down",
            "In, oh, so many ways",
            "How you gonna see me now?",
            "Since we've been on our own",
            "Are you gonna love the man",
            "When the man gets home?",
            "How you gonna see me now?",
            "Please don't see me ugly, babe",
            "'Cause I know I let you down",
            "In, oh, so many ways",
            "How you gonna see me now?",
            "Since we've been on our own",
            "Are you gonna love the man",
            "When the man gets home?",
            "",
            "[Outro]",
            "Yeah, yeah",
            "Oh, so many waysEmbed"
        ],
        "Pre-Chorus": [],
        "Bridge": [
            "And just like the first time, we're just strangers again",
            "I might have grown out of style in the place I've been",
            "And just like the first time, I'll be shakin' inside",
            "When I walk in the door, there'll be no place to hide",
            "",
            "[Break]",
            "How you gonna see me now?",
            "Please don't see me ugly, babe",
            "'Cause I feel I let you down",
            "In, oh, so many ways",
            ""
        ]
    },
    "spotify_metadata": {
        "energy": 0.336,
        "acousticness": 0.458,
        "danceability": 0.543,
        "instrumentalness": 3.48e-06,
        "liveness": 0.133,
        "speechiness": 0.0381,
        "loudness": -14.413,
        "tempo": 136.066,
        "time_signature": 4,
        "valence": 0.299,
        "genre": [
            "album rock",
            "classic rock",
            "detroit rock",
            "glam metal",
            "glam rock",
            "hard rock",
            "metal",
            "protopunk",
            "rock"
        ],
        "popularity": 0
    }
}