{
    "midi_file_path": "archive-new\\Bad_Company\\Feel_Like_Makin_Love.1.mid",
    "artist_band_name": "Bad Company",
    "song_title": "Feel Like Makin Love.1",
    "lyrics": {
        "Verse": [
            "Baby, when I think about you",
            "I think about love",
            "Darlin', don't live without you",
            "And your love",
            "",
            "Baby, if I think about you",
            "I Think about love",
            "Darlin', if I live without you",
            "I live without love"
        ],
        "Chorus": [
            "Feel like makin'",
            "Feel like makin' love",
            "Feel like makin' love",
            "Feel like makin' love",
            "Feel like makin' love to you",
            "",
            "Feel like makin'",
            "Feel like makin' love",
            "Feel like makin' love",
            "Feel like makin' love",
            "Feel like makin' love to you",
            "",
            "[Instrumental Break]",
            "",
            "Feel like makin'",
            "Feel like makin' love",
            "Feel like makin' love",
            "Feel like makin' love",
            "Feel like makin' love to you",
            "[Outro]",
            "Well I feel like makin' love",
            "Well I feel like makin' love",
            "Well I feel like makin' love",
            "Feel like makin' love to you",
            "Well I feel like makin' love (yeah)",
            "Well I feel like makin' love (yeah)",
            "Well I feel like makin' love (yeah)",
            "Feel like makin' love to you",
            "Well I feel like makin' love",
            "Well I feel like makin' love",
            "Well I feel like makin' love",
            "Feel like makin' love to you2Embed"
        ],
        "Pre-Chorus": [],
        "Bridge": [
            "If I had, those golden dreams",
            "Of my yesterdays",
            "I would wrap you, in the heaven",
            "'Til I'm dyin' (dyin', dyin',)",
            "On the way",
            "",
            "And if I had, the sun and moon",
            "And they were shinin' (shinin')",
            "I would give you, both night and day",
            "Love satisfyin'",
            "",
            "And if I had, those golden dreams",
            "Of my yesterdays",
            "I would wrap you, in the heaven",
            "'Til I'm dyin' (dyin', dyin',)",
            "On the way",
            ""
        ]
    },
    "spotify_metadata": {
        "energy": 0.688,
        "acousticness": 0.131,
        "danceability": 0.389,
        "instrumentalness": 0.00291,
        "liveness": 0.974,
        "speechiness": 0.0311,
        "loudness": -7.433,
        "tempo": 84.83,
        "time_signature": 4,
        "valence": 0.638,
        "genre": [
            "album rock",
            "classic rock",
            "country rock",
            "glam metal",
            "hard rock",
            "mellow gold",
            "rock",
            "singer-songwriter",
            "soft rock",
            "southern rock"
        ],
        "popularity": 11
    }
}